function_ext_monitor/__init__.py
function_ext_monitor-0.0.6.dist-info/LICENSE
function_ext_monitor-0.0.6.dist-info/METADATA
function_ext_monitor-0.0.6.dist-info/WHEEL
function_ext_monitor-0.0.6.dist-info/top_level.txt
function_ext_monitor-0.0.6.dist-info/RECORD
